cogsworth/__init__.py
cogsworth/_version.py
cogsworth/citations.py
cogsworth/classify.py
cogsworth/events.py
cogsworth/kicks.py
cogsworth/plot.py
cogsworth/pop.py
cogsworth/sfh.py
cogsworth/utils.py
cogsworth/hydro/__init__.py
cogsworth/hydro/pop.py
cogsworth/hydro/potential.py
cogsworth/hydro/rewind.py
cogsworth/hydro/utils.py
cogsworth/obs/__init__.py
cogsworth/obs/mist.py
cogsworth/obs/observables.py
cogsworth/tests/__init__.py
cogsworth/tests/optional_deps.py
cogsworth/tests/runtime.py
cogsworth/tests/test_citations.py
cogsworth/tests/test_classify.py
cogsworth/tests/test_events.py
cogsworth/tests/test_hydro.py
cogsworth/tests/test_kicks.py
cogsworth/tests/test_mist.py
cogsworth/tests/test_observables.py
cogsworth/tests/test_plot.py
cogsworth/tests/test_pop.py
cogsworth/tests/test_sfh.py
cogsworth-3.6.1.dist-info/licenses/LICENSE
cogsworth-3.6.1.dist-info/METADATA
cogsworth-3.6.1.dist-info/WHEEL
cogsworth-3.6.1.dist-info/top_level.txt
cogsworth-3.6.1.dist-info/RECORD
