Metadata-Version: 2.4
Name: cogsworth
Version: 3.6.1
Summary: A framework for performing self-consistent population synthesis and orbital integration
Home-page: https://github.com/TomWagg/cogsworth
Author: Tom Wagg
Author-email: tomjwagg@gmail.com
License: MIT
Requires-Python: >=3.11
License-File: LICENSE
Requires-Dist: numpy>=1.23
Requires-Dist: numba>=0.58
Requires-Dist: pip
Requires-Dist: matplotlib>=3.7
Requires-Dist: astropy>=5.0
Requires-Dist: scipy>=1.8
Requires-Dist: pandas>=2.1
Requires-Dist: gala>=1.11.0
Requires-Dist: cosmic-popsynth>=3.6.2
Provides-Extra: all
Requires-Dist: dustmaps; extra == "all"
Requires-Dist: healpy; extra == "all"
Requires-Dist: gaiaunlimited>=0.2.0; extra == "all"
Requires-Dist: agama; extra == "all"
Requires-Dist: dustmaps; extra == "all"
Requires-Dist: healpy; extra == "all"
Requires-Dist: gaiaunlimited>=0.2.0; extra == "all"
Requires-Dist: legwork>=0.4.6; extra == "all"
Requires-Dist: pynbody>=2.0.0; extra == "all"
Requires-Dist: agama; extra == "all"
Requires-Dist: pytest; extra == "all"
Requires-Dist: flake8; extra == "all"
Requires-Dist: coverage; extra == "all"
Requires-Dist: pytest-xdist; extra == "all"
Requires-Dist: nbmake; extra == "all"
Requires-Dist: pytest-cov; extra == "all"
Requires-Dist: dustmaps; extra == "all"
Requires-Dist: healpy; extra == "all"
Requires-Dist: gaiaunlimited>=0.2.0; extra == "all"
Requires-Dist: pynbody>=2.0.0; extra == "all"
Requires-Dist: sphinx<7.2; extra == "all"
Requires-Dist: matplotlib<3.9; extra == "all"
Requires-Dist: nbsphinx>=0.8.6; extra == "all"
Requires-Dist: numpydoc; extra == "all"
Requires-Dist: pydata-sphinx-theme; extra == "all"
Requires-Dist: sphinx_automodapi; extra == "all"
Requires-Dist: sphinxcontrib.bibtex; extra == "all"
Requires-Dist: IPython; extra == "all"
Requires-Dist: ipykernel; extra == "all"
Requires-Dist: sphinx_copybutton; extra == "all"
Requires-Dist: sphinx-gallery>=0.13.0; extra == "all"
Requires-Dist: sphinx-design>=0.4.1; extra == "all"
Requires-Dist: sphinx_togglebutton; extra == "all"
Provides-Extra: extras
Requires-Dist: dustmaps; extra == "extras"
Requires-Dist: healpy; extra == "extras"
Requires-Dist: gaiaunlimited>=0.2.0; extra == "extras"
Requires-Dist: agama; extra == "extras"
Requires-Dist: pynbody>=2.0.0; extra == "extras"
Requires-Dist: legwork>=0.4.6; extra == "extras"
Provides-Extra: observables
Requires-Dist: dustmaps; extra == "observables"
Requires-Dist: healpy; extra == "observables"
Requires-Dist: gaiaunlimited>=0.2.0; extra == "observables"
Provides-Extra: actions
Requires-Dist: agama; extra == "actions"
Provides-Extra: lisa
Requires-Dist: legwork>=0.4.6; extra == "lisa"
Provides-Extra: hydro
Requires-Dist: pynbody>=2.0.0; extra == "hydro"
Provides-Extra: test
Requires-Dist: dustmaps; extra == "test"
Requires-Dist: healpy; extra == "test"
Requires-Dist: gaiaunlimited>=0.2.0; extra == "test"
Requires-Dist: legwork>=0.4.6; extra == "test"
Requires-Dist: pynbody>=2.0.0; extra == "test"
Requires-Dist: agama; extra == "test"
Requires-Dist: pytest; extra == "test"
Requires-Dist: flake8; extra == "test"
Requires-Dist: coverage; extra == "test"
Requires-Dist: pytest-xdist; extra == "test"
Requires-Dist: nbmake; extra == "test"
Requires-Dist: pytest-cov; extra == "test"
Provides-Extra: docs
Requires-Dist: dustmaps; extra == "docs"
Requires-Dist: healpy; extra == "docs"
Requires-Dist: gaiaunlimited>=0.2.0; extra == "docs"
Requires-Dist: pynbody>=2.0.0; extra == "docs"
Requires-Dist: sphinx<7.2; extra == "docs"
Requires-Dist: matplotlib<3.9; extra == "docs"
Requires-Dist: nbsphinx>=0.8.6; extra == "docs"
Requires-Dist: numpydoc; extra == "docs"
Requires-Dist: pydata-sphinx-theme; extra == "docs"
Requires-Dist: sphinx_automodapi; extra == "docs"
Requires-Dist: sphinxcontrib.bibtex; extra == "docs"
Requires-Dist: IPython; extra == "docs"
Requires-Dist: ipykernel; extra == "docs"
Requires-Dist: sphinx_copybutton; extra == "docs"
Requires-Dist: sphinx-gallery>=0.13.0; extra == "docs"
Requires-Dist: sphinx-design>=0.4.1; extra == "docs"
Requires-Dist: sphinx_togglebutton; extra == "docs"
Dynamic: license-file
